{
  "重庆西站": [
    [
      "环",
      "01"
    ],
    [
      "05",
      "25"
    ]
  ],
  "上桥": [
    [
      "环",
      "02"
    ]
  ],
  "凤鸣山": [
    [
      "环",
      "03"
    ]
  ],
  "重庆图书馆": [
    [
      "环",
      "04"
    ]
  ],
  "天星桥": [
    [
      "环",
      "05"
    ]
  ],
  "沙坪坝": [
    [
      "环",
      "06"
    ],
    [
      "01",
      "14"
    ],
    [
      "09",
      "04"
    ]
  ],
  "重庆大学": [
    [
      "环",
      "07"
    ]
  ],
  "玉带山": [
    [
      "环",
      "08"
    ],
    [
      "04",
      "03"
    ]
  ],
  "南桥寺": [
    [
      "环",
      "09"
    ]
  ],
  "体育公园": [
    [
      "环",
      "10"
    ]
  ],
  "冉家坝": [
    [
      "环",
      "11"
    ],
    [
      "05",
      "15"
    ],
    [
      "06",
      "15"
    ]
  ],
  "动步公园": [
    [
      "环",
      "12"
    ]
  ],
  "洪湖东路": [
    [
      "环",
      "13"
    ]
  ],
  "民安大道": [
    [
      "环",
      "14"
    ],
    [
      "04",
      "10"
    ]
  ],
  "重庆北站南广场": [
    [
      "环",
      "15"
    ],
    [
      "03",
      "27"
    ],
    [
      "10",
      "12"
    ]
  ],
  "渝鲁": [
    [
      "环",
      "16"
    ]
  ],
  "五里店": [
    [
      "环",
      "17"
    ],
    [
      "06",
      "09"
    ],
    [
      "09",
      "16"
    ]
  ],
  "弹子石": [
    [
      "环",
      "18"
    ]
  ],
  "涂山": [
    [
      "环",
      "19"
    ]
  ],
  "仁济": [
    [
      "环",
      "20"
    ]
  ],
  "上浩": [
    [
      "环",
      "22"
    ]
  ],
  "海棠溪": [
    [
      "环",
      "23"
    ]
  ],
  "罗家坝": [
    [
      "环",
      "24"
    ]
  ],
  "四公里": [
    [
      "环",
      "25"
    ],
    [
      "03",
      "14"
    ]
  ],
  "南湖": [
    [
      "环",
      "26"
    ],
    [
      "10",
      "02"
    ]
  ],
  "海峡路": [
    [
      "环",
      "27"
    ]
  ],
  "谢家湾": [
    [
      "环",
      "28"
    ],
    [
      "02",
      "11"
    ]
  ],
  "奥体中心": [
    [
      "环",
      "29"
    ],
    [
      "18",
      "03"
    ]
  ],
  "陈家坪": [
    [
      "环",
      "30"
    ]
  ],
  "彩云湖": [
    [
      "环",
      "31"
    ]
  ],
  "二郎": [
    [
      "环",
      "32"
    ]
  ],
  "华龙": [
    [
      "环",
      "33"
    ]
  ],
  "朝天门": [
    [
      "01",
      "01"
    ]
  ],
  "小什字": [
    [
      "01",
      "02"
    ],
    [
      "06",
      "06"
    ]
  ],
  "较场口": [
    [
      "01",
      "03"
    ],
    [
      "02",
      "01"
    ]
  ],
  "七星岗": [
    [
      "01",
      "04"
    ],
    [
      "10",
      "06"
    ]
  ],
  "两路口": [
    [
      "01",
      "05"
    ],
    [
      "03",
      "18"
    ]
  ],
  "鹅岭": [
    [
      "01",
      "06"
    ]
  ],
  "大坪": [
    [
      "01",
      "07"
    ],
    [
      "02",
      "09"
    ]
  ],
  "石油路": [
    [
      "01",
      "08"
    ]
  ],
  "歇台子": [
    [
      "01",
      "09"
    ],
    [
      "05",
      "20"
    ],
    [
      "18",
      "02"
    ]
  ],
  "石桥铺": [
    [
      "01",
      "10"
    ],
    [
      "05",
      "21"
    ]
  ],
  "高庙村": [
    [
      "01",
      "11"
    ]
  ],
  "马家岩": [
    [
      "01",
      "12"
    ]
  ],
  "小龙坎": [
    [
      "01",
      "13"
    ],
    [
      "09",
      "05"
    ]
  ],
  "杨公桥": [
    [
      "01",
      "15"
    ]
  ],
  "烈士墓": [
    [
      "01",
      "16"
    ]
  ],
  "磁器口": [
    [
      "01",
      "17"
    ]
  ],
  "石井坡": [
    [
      "01",
      "18"
    ]
  ],
  "双碑": [
    [
      "01",
      "19"
    ]
  ],
  "赖家桥": [
    [
      "01",
      "20"
    ]
  ],
  "微电园": [
    [
      "01",
      "21"
    ]
  ],
  "陈家桥": [
    [
      "01",
      "22"
    ]
  ],
  "大学城": [
    [
      "01",
      "23"
    ]
  ],
  "尖顶坡": [
    [
      "01",
      "24"
    ]
  ],
  "璧山": [
    [
      "01",
      "25"
    ],
    [
      "璧铜",
      "09"
    ]
  ],
  "临江门": [
    [
      "02",
      "02"
    ]
  ],
  "黄花园": [
    [
      "02",
      "03"
    ]
  ],
  "大溪沟": [
    [
      "02",
      "04"
    ]
  ],
  "曾家岩": [
    [
      "02",
      "05"
    ],
    [
      "10",
      "08"
    ]
  ],
  "牛角沱": [
    [
      "02",
      "06"
    ],
    [
      "03",
      "19"
    ]
  ],
  "李子坝": [
    [
      "02",
      "07"
    ]
  ],
  "佛图关": [
    [
      "02",
      "08"
    ]
  ],
  "袁家岗": [
    [
      "02",
      "10"
    ]
  ],
  "杨家坪": [
    [
      "02",
      "12"
    ],
    [
      "18",
      "05"
    ]
  ],
  "动物园": [
    [
      "02",
      "13"
    ]
  ],
  "大堰村": [
    [
      "02",
      "14"
    ]
  ],
  "平安": [
    [
      "02",
      "16"
    ]
  ],
  "大渡口": [
    [
      "02",
      "17"
    ]
  ],
  "新山村": [
    [
      "02",
      "18"
    ]
  ],
  "天堂堡": [
    [
      "02",
      "19"
    ]
  ],
  "建桥": [
    [
      "02",
      "20"
    ]
  ],
  "金家湾": [
    [
      "02",
      "21"
    ]
  ],
  "刘家坝": [
    [
      "02",
      "22"
    ]
  ],
  "白居寺": [
    [
      "02",
      "23"
    ],
    [
      "18",
      "15"
    ]
  ],
  "大江": [
    [
      "02",
      "24"
    ]
  ],
  "鱼洞": [
    [
      "02",
      "25"
    ],
    [
      "03",
      "01"
    ]
  ],
  "金竹": [
    [
      "03",
      "02"
    ]
  ],
  "鱼胡路": [
    [
      "03",
      "03"
    ]
  ],
  "学堂湾": [
    [
      "03",
      "04"
    ]
  ],
  "大山村": [
    [
      "03",
      "05"
    ]
  ],
  "花溪": [
    [
      "03",
      "06"
    ]
  ],
  "岔路口": [
    [
      "03",
      "07"
    ]
  ],
  "九公里": [
    [
      "03",
      "08"
    ]
  ],
  "麒龙": [
    [
      "03",
      "09"
    ]
  ],
  "八公里": [
    [
      "03",
      "10"
    ]
  ],
  "重庆交通大学": [
    [
      "03",
      "11"
    ]
  ],
  "六公里": [
    [
      "03",
      "12"
    ]
  ],
  "重庆工商大学": [
    [
      "03",
      "13"
    ]
  ],
  "南坪": [
    [
      "03",
      "15"
    ],
    [
      "10",
      "04"
    ]
  ],
  "工贸": [
    [
      "03",
      "16"
    ]
  ],
  "铜元局": [
    [
      "03",
      "17"
    ]
  ],
  "华新街": [
    [
      "03",
      "20"
    ]
  ],
  "观音桥": [
    [
      "03",
      "21"
    ],
    [
      "09",
      "12"
    ]
  ],
  "红旗河沟": [
    [
      "03",
      "22"
    ],
    [
      "06",
      "12"
    ]
  ],
  "嘉州路": [
    [
      "03",
      "23"
    ]
  ],
  "郑家院子": [
    [
      "03",
      "24"
    ]
  ],
  "唐家院子": [
    [
      "03",
      "25"
    ]
  ],
  "狮子坪": [
    [
      "03",
      "26"
    ]
  ],
  "龙头寺": [
    [
      "03",
      "28"
    ]
  ],
  "童家院子": [
    [
      "03",
      "29"
    ]
  ],
  "金渝": [
    [
      "03",
      "30"
    ]
  ],
  "金童路": [
    [
      "03",
      "31"
    ]
  ],
  "鸳鸯": [
    [
      "03",
      "32"
    ]
  ],
  "园博园": [
    [
      "03",
      "33"
    ]
  ],
  "翠云": [
    [
      "03",
      "34"
    ]
  ],
  "长福路": [
    [
      "03",
      "35"
    ]
  ],
  "回兴": [
    [
      "03",
      "36"
    ]
  ],
  "双龙": [
    [
      "03",
      "37"
    ]
  ],
  "碧津": [
    [
      "03",
      "38"
    ]
  ],
  "江北机场T2航站楼": [
    [
      "03",
      "39"
    ],
    [
      "10",
      "20"
    ]
  ],
  "双凤桥": [
    [
      "03",
      "40"
    ]
  ],
  "空港广场": [
    [
      "03",
      "41"
    ]
  ],
  "高堡湖": [
    [
      "03",
      "42"
    ]
  ],
  "观月路": [
    [
      "03",
      "43"
    ]
  ],
  "莲花": [
    [
      "03",
      "44"
    ]
  ],
  "举人坝": [
    [
      "03",
      "45"
    ]
  ],
  "重庆北站北广场": [
    [
      "10",
      "13"
    ],
    [
      "04",
      "11"
    ]
  ],
  "头塘": [
    [
      "09",
      "18"
    ],
    [
      "04",
      "12"
    ]
  ],
  "保税港": [
    [
      "09",
      "19"
    ],
    [
      "04",
      "13"
    ]
  ],
  "寸滩": [
    [
      "04",
      "14"
    ]
  ],
  "黑石子": [
    [
      "04",
      "15"
    ]
  ],
  "港城": [
    [
      "04",
      "16"
    ]
  ],
  "太平冲": [
    [
      "04",
      "17"
    ]
  ],
  "唐家沱": [
    [
      "04",
      "18"
    ]
  ],
  "铁山坪": [
    [
      "04",
      "19"
    ]
  ],
  "鹿栖": [
    [
      "04",
      "20"
    ]
  ],
  "果园物流枢纽": [
    [
      "04",
      "21"
    ]
  ],
  "鱼嘴": [
    [
      "04",
      "22"
    ]
  ],
  "雁坪": [
    [
      "04",
      "23"
    ]
  ],
  "石河清": [
    [
      "04",
      "24"
    ]
  ],
  "复盛": [
    [
      "04",
      "25"
    ]
  ],
  "三板溪": [
    [
      "04",
      "26"
    ]
  ],
  "龙驿大道": [
    [
      "04",
      "27"
    ]
  ],
  "龙兴": [
    [
      "04",
      "28"
    ]
  ],
  "高石塔": [
    [
      "04",
      "29"
    ]
  ],
  "普福": [
    [
      "04",
      "30"
    ]
  ],
  "桐梓林": [
    [
      "04",
      "31"
    ]
  ],
  "石船": [
    [
      "04",
      "32"
    ]
  ],
  "黄岭": [
    [
      "04",
      "33"
    ]
  ],
  "悦港北路": [
    [
      "05",
      "01"
    ]
  ],
  "悦港大道": [
    [
      "05",
      "02"
    ]
  ],
  "椿萱大道": [
    [
      "05",
      "03"
    ]
  ],
  "中央公园西": [
    [
      "05",
      "04"
    ],
    [
      "10",
      "25"
    ]
  ],
  "鲁家沟": [
    [
      "05",
      "05"
    ]
  ],
  "玉河沟": [
    [
      "05",
      "07"
    ]
  ],
  "园博中心": [
    [
      "05",
      "08"
    ]
  ],
  "丹鹤": [
    [
      "05",
      "09"
    ]
  ],
  "湖霞街": [
    [
      "05",
      "10"
    ]
  ],
  "重光": [
    [
      "05",
      "11"
    ]
  ],
  "和睦路": [
    [
      "05",
      "12"
    ]
  ],
  "人和": [
    [
      "05",
      "13"
    ]
  ],
  "幸福广场": [
    [
      "05",
      "14"
    ]
  ],
  "大龙山": [
    [
      "05",
      "16"
    ],
    [
      "06",
      "14"
    ]
  ],
  "大石坝": [
    [
      "05",
      "17"
    ]
  ],
  "忠恕沱": [
    [
      "05",
      "18"
    ]
  ],
  "红岩村": [
    [
      "05",
      "19"
    ],
    [
      "09",
      "07"
    ]
  ],
  "石新路": [
    [
      "05",
      "22"
    ]
  ],
  "巴山": [
    [
      "05",
      "23"
    ]
  ],
  "凤西路": [
    [
      "05",
      "24"
    ]
  ],
  "华岩寺": [
    [
      "05",
      "26"
    ]
  ],
  "华成路": [
    [
      "05",
      "27"
    ]
  ],
  "半山": [
    [
      "05",
      "28"
    ]
  ],
  "中梁山": [
    [
      "05",
      "29"
    ]
  ],
  "金建路": [
    [
      "05",
      "30"
    ]
  ],
  "华岩中心": [
    [
      "05",
      "31"
    ]
  ],
  "跳磴": [
    [
      "05",
      "32"
    ],
    [
      "18",
      "18"
    ],
    [
      "江跳",
      "01"
    ]
  ],
  "石林寺": [
    [
      "江跳",
      "02"
    ]
  ],
  "九龙园": [
    [
      "江跳",
      "03"
    ]
  ],
  "双福": [
    [
      "江跳",
      "04"
    ]
  ],
  "享堂": [
    [
      "江跳",
      "05"
    ]
  ],
  "圣泉寺": [
    [
      "江跳",
      "07"
    ]
  ],
  "茶园": [
    [
      "06",
      "01"
    ]
  ],
  "邱家湾": [
    [
      "06",
      "02"
    ]
  ],
  "长生桥": [
    [
      "06",
      "03"
    ]
  ],
  "刘家坪": [
    [
      "06",
      "04"
    ]
  ],
  "上新街": [
    [
      "环",
      "21"
    ],
    [
      "06",
      "05"
    ]
  ],
  "大剧院": [
    [
      "06",
      "07"
    ]
  ],
  "江北城": [
    [
      "06",
      "08"
    ],
    [
      "09",
      "15"
    ]
  ],
  "红土地": [
    [
      "06",
      "10"
    ],
    [
      "10",
      "10"
    ]
  ],
  "花卉园": [
    [
      "06",
      "13"
    ]
  ],
  "光电园": [
    [
      "06",
      "16"
    ]
  ],
  "大竹林": [
    [
      "06",
      "17"
    ]
  ],
  "康庄": [
    [
      "06",
      "18"
    ]
  ],
  "金山寺": [
    [
      "06",
      "21"
    ]
  ],
  "礼嘉": [
    [
      "06",
      "20"
    ],
    [
      "国博",
      "20"
    ]
  ],
  "曹家湾": [
    [
      "06",
      "22"
    ]
  ],
  "蔡家": [
    [
      "06",
      "23"
    ]
  ],
  "向家岗": [
    [
      "06",
      "24"
    ]
  ],
  "龙凤溪": [
    [
      "06",
      "25"
    ]
  ],
  "北碚": [
    [
      "06",
      "28"
    ]
  ],
  "欢乐谷": [
    [
      "国博",
      "29"
    ]
  ],
  "黄茅坪": [
    [
      "国博",
      "30"
    ]
  ],
  "高义口": [
    [
      "国博",
      "31"
    ]
  ],
  "国博中心": [
    [
      "国博",
      "32"
    ]
  ],
  "悦来": [
    [
      "10",
      "26"
    ],
    [
      "国博",
      "33"
    ]
  ],
  "王家庄": [
    [
      "10",
      "27"
    ],
    [
      "国博",
      "34"
    ]
  ],
  "清溪河": [
    [
      "国博",
      "35"
    ]
  ],
  "刘家院子": [
    [
      "国博",
      "36"
    ]
  ],
  "思源": [
    [
      "国博",
      "37"
    ]
  ],
  "复兴": [
    [
      "国博",
      "38"
    ]
  ],
  "红岩坪": [
    [
      "国博",
      "39"
    ]
  ],
  "沙河坝": [
    [
      "国博",
      "40"
    ]
  ],
  "高滩岩": [
    [
      "09",
      "02"
    ]
  ],
  "天梨路": [
    [
      "09",
      "03"
    ]
  ],
  "土湾": [
    [
      "09",
      "06"
    ]
  ],
  "富华路": [
    [
      "18",
      "01"
    ],
    [
      "09",
      "08"
    ]
  ],
  "化龙桥": [
    [
      "09",
      "09"
    ]
  ],
  "李家坪": [
    [
      "09",
      "10"
    ]
  ],
  "鲤鱼池": [
    [
      "10",
      "09"
    ],
    [
      "09",
      "13"
    ]
  ],
  "溉澜溪": [
    [
      "09",
      "17"
    ]
  ],
  "何家梁": [
    [
      "09",
      "21"
    ]
  ],
  "上湾路": [
    [
      "10",
      "16"
    ],
    [
      "09",
      "23"
    ]
  ],
  "青岗坪": [
    [
      "09",
      "24"
    ]
  ],
  "宝圣湖": [
    [
      "09",
      "25"
    ]
  ],
  "兴科大道": [
    [
      "09",
      "26"
    ]
  ],
  "春华大道": [
    [
      "09",
      "27"
    ]
  ],
  "兰桂大道": [
    [
      "09",
      "28"
    ]
  ],
  "中央公园东": [
    [
      "10",
      "23"
    ],
    [
      "09",
      "29"
    ]
  ],
  "丛岩寺": [
    [
      "09",
      "30"
    ]
  ],
  "花石沟": [
    [
      "09",
      "31"
    ]
  ],
  "兰花路": [
    [
      "10",
      "01"
    ]
  ],
  "万寿路": [
    [
      "10",
      "03"
    ]
  ],
  "后堡": [
    [
      "10",
      "05"
    ]
  ],
  "大礼堂": [
    [
      "10",
      "07"
    ]
  ],
  "龙头寺公园": [
    [
      "10",
      "11"
    ]
  ],
  "民心佳园": [
    [
      "10",
      "14"
    ]
  ],
  "三亚湾": [
    [
      "10",
      "15"
    ]
  ],
  "环山公园": [
    [
      "10",
      "17"
    ]
  ],
  "长河": [
    [
      "10",
      "18"
    ]
  ],
  "江北机场T3航站楼": [
    [
      "10",
      "19"
    ]
  ],
  "渝北广场": [
    [
      "10",
      "21"
    ]
  ],
  "鹿山": [
    [
      "10",
      "22"
    ]
  ],
  "中央公园": [
    [
      "10",
      "24"
    ]
  ],
  "石坪桥": [
    [
      "18",
      "04"
    ]
  ],
  "滩子口": [
    [
      "18",
      "06"
    ]
  ],
  "黄桷坪": [
    [
      "18",
      "07"
    ]
  ],
  "四川美术学院": [
    [
      "18",
      "08"
    ]
  ],
  "电厂": [
    [
      "18",
      "09"
    ]
  ],
  "李家沱大桥": [
    [
      "18",
      "10"
    ]
  ],
  "重庆理工大学": [
    [
      "18",
      "11"
    ]
  ],
  "花溪工业园": [
    [
      "18",
      "12"
    ]
  ],
  "巴滨路湿地公园": [
    [
      "18",
      "13"
    ]
  ],
  "茄子溪": [
    [
      "18",
      "14"
    ]
  ],
  "伏牛溪": [
    [
      "18",
      "16"
    ]
  ],
  "金鳌山": [
    [
      "18",
      "17"
    ]
  ],
  "跳磴南": [
    [
      "18",
      "19"
    ]
  ],
  "璧城": [
    [
      "璧铜",
      "08"
    ]
  ],
  "河边": [
    [
      "璧铜",
      "07"
    ]
  ],
  "青龙湖": [
    [
      "璧铜",
      "06"
    ]
  ],
  "大路": [
    [
      "璧铜",
      "05"
    ]
  ],
  "庆隆": [
    [
      "璧铜",
      "04"
    ]
  ],
  "科创新城": [
    [
      "璧铜",
      "03"
    ]
  ],
  "铜梁龙城天街": [
    [
      "璧铜",
      "02"
    ]
  ],
  "铜梁西": [
    [
      "璧铜",
      "01"
    ]
  ],
  "重庆东站": [
    [
      "06",
      "41"
    ]
  ],
  "百乐园": [
    [
      "06",
      "43"
    ]
  ],
  "桃花桥": [
    [
      "06",
      "42"
    ]
  ],
  "黄泥塝": [
    [
      "06",
      "11"
    ]
  ],
  "九曲河": [
    [
      "06",
      "19"
    ]
  ],
  "状元碑": [
    [
      "06",
      "26"
    ]
  ],
  "西南大学": [
    [
      "06",
      "27"
    ]
  ],
  "邮轮母港": [
    [
      "09",
      "20"
    ]
  ],
  "新桥": [
    [
      "09",
      "01"
    ]
  ],
  "蚂蝗梁": [
    [
      "09",
      "11"
    ]
  ],
  "刘家台": [
    [
      "09",
      "14"
    ]
  ],
  "石盘河": [
    [
      "09",
      "22"
    ]
  ],
  "马王场": [
    [
      "02",
      "15"
    ]
  ],
  "甘悦大道": [
    [
      "05",
      "06"
    ]
  ],
  "江津高铁": [
    [
      "江跳",
      "06"
    ]
  ],
  "几江": [
    [
      "江跳",
      "08"
    ]
  ],
  "鼎山": [
    [
      "江跳",
      "09"
    ]
  ],
  "顺水寺公园": [
    [
      "04",
      "01"
    ]
  ],
  "石马河立交": [
    [
      "04",
      "02"
    ]
  ],
  "盘溪": [
    [
      "04",
      "04"
    ]
  ],
  "大庆村": [
    [
      "04",
      "06"
    ]
  ],
  "龙溪": [
    [
      "04",
      "08"
    ]
  ]
}